LICENSE
MANIFEST.in
README.md
quicktest.py
settings_test.py
setup.py
django_instagram_api.egg-info/PKG-INFO
django_instagram_api.egg-info/SOURCES.txt
django_instagram_api.egg-info/dependency_links.txt
django_instagram_api.egg-info/not-zip-safe
django_instagram_api.egg-info/requires.txt
django_instagram_api.egg-info/top_level.txt
instagram_api/__init__.py
instagram_api/__init__.pyc
instagram_api/admin.py
instagram_api/admin.pyc
instagram_api/api.py
instagram_api/api.pyc
instagram_api/decorators.py
instagram_api/decorators.pyc
instagram_api/factories.py
instagram_api/factories.pyc
instagram_api/fields.py
instagram_api/fields.pyc
instagram_api/models.py
instagram_api/models.pyc
instagram_api/tests.py
instagram_api/tests.pyc
instagram_api/migrations/0001_initial.py
instagram_api/migrations/0001_initial.pyc
instagram_api/migrations/0002_user_follows_count.py
instagram_api/migrations/0002_user_follows_count.pyc
instagram_api/migrations/0003_user_is_private.py
instagram_api/migrations/0003_user_is_private.pyc
instagram_api/migrations/0004_location.py
instagram_api/migrations/0004_location.pyc
instagram_api/migrations/0005_auto_20160212_0204.py
instagram_api/migrations/0005_auto_20160212_0204.pyc
instagram_api/migrations/0006_media_filter.py
instagram_api/migrations/0006_media_filter.pyc
instagram_api/migrations/0007_auto_20160212_0346.py
instagram_api/migrations/0007_auto_20160212_0346.pyc
instagram_api/migrations/0008_auto_20160212_1345.py
instagram_api/migrations/0008_auto_20160212_1345.pyc
instagram_api/migrations/0009_auto_20160212_1454.py
instagram_api/migrations/0009_auto_20160212_1454.pyc
instagram_api/migrations/0010_auto_20160212_1602.py
instagram_api/migrations/0010_auto_20160212_1602.pyc
instagram_api/migrations/0011_auto_20160213_0338.py
instagram_api/migrations/0011_auto_20160213_0338.pyc
instagram_api/migrations/0012_auto_20160215_0123.py
instagram_api/migrations/0012_auto_20160215_0123.pyc
instagram_api/migrations/__init__.py
instagram_api/migrations/__init__.pyc