Metadata-Version: 1.1
Name: django-instagram-api
Version: 0.3.4
Summary: Django implementation for instagram API
Home-page: https://github.com/ramusus/django-instagram-api
Author: krupin.dv
Author-email: krupin.dv19@gmail.com
License: BSD
Download-URL: http://pypi.python.org/pypi/django-instagram-api
Platform: UNKNOWN
Classifier: Development Status :: 4 - Beta
Classifier: Environment :: Web Environment
Classifier: Intended Audience :: Developers
Classifier: License :: OSI Approved :: BSD License
Classifier: Operating System :: OS Independent
Classifier: Programming Language :: Python
Classifier: Topic :: Software Development :: Libraries :: Python Modules
